docs/Makefile
docs/conf.py
docs/make.bat
docs/_static/custom.css
docs/_static/konami.js
docs/_static/pipenv.png
docs/_templates/hacks.html
docs/_templates/sidebarlogo.html
pipenv/__init__.py
pipenv/__main__.py
pipenv/__version__.py
pipenv/cmdparse.py
pipenv/environment.py
pipenv/environments.py
pipenv/exceptions.py
pipenv/help.py
pipenv/installers.py
pipenv/pep508checker.py
pipenv/pipenv.1
pipenv/project.py
pipenv/resolver.py
pipenv/shells.py
pipenv/cli/__init__.py
pipenv/cli/command.py
pipenv/cli/options.py
pipenv/patched/README.md
pipenv/patched/__init__.py
pipenv/patched/patched.txt
pipenv/patched/pip/COPYING
pipenv/patched/pip/LICENSE
pipenv/patched/pip/LICENSE-HEADER
pipenv/patched/pip/LICENSE.APACHE
pipenv/patched/pip/LICENSE.BSD
pipenv/patched/pip/LICENSE.md
pipenv/patched/pip/LICENSE.txt
pipenv/patched/pip/__init__.py
pipenv/patched/pip/__main__.py
pipenv/patched/pip/__pip-runner__.py
pipenv/patched/pip/py.typed
pipenv/patched/pip/typing_extensions.LICENSE
pipenv/patched/pip/_internal/__init__.py
pipenv/patched/pip/_internal/build_env.py
pipenv/patched/pip/_internal/cache.py
pipenv/patched/pip/_internal/configuration.py
pipenv/patched/pip/_internal/exceptions.py
pipenv/patched/pip/_internal/main.py
pipenv/patched/pip/_internal/pyproject.py
pipenv/patched/pip/_internal/self_outdated_check.py
pipenv/patched/pip/_internal/wheel_builder.py
pipenv/patched/pip/_internal/cli/__init__.py
pipenv/patched/pip/_internal/cli/autocompletion.py
pipenv/patched/pip/_internal/cli/base_command.py
pipenv/patched/pip/_internal/cli/cmdoptions.py
pipenv/patched/pip/_internal/cli/command_context.py
pipenv/patched/pip/_internal/cli/index_command.py
pipenv/patched/pip/_internal/cli/main.py
pipenv/patched/pip/_internal/cli/main_parser.py
pipenv/patched/pip/_internal/cli/parser.py
pipenv/patched/pip/_internal/cli/progress_bars.py
pipenv/patched/pip/_internal/cli/req_command.py
pipenv/patched/pip/_internal/cli/spinners.py
pipenv/patched/pip/_internal/cli/status_codes.py
pipenv-2025.0.0.dist-info/licenses/LICENSE
pipenv-2025.0.0.dist-info/licenses/NOTICES
pipenv-2025.0.0.dist-info/METADATA
pipenv-2025.0.0.dist-info/WHEEL
pipenv-2025.0.0.dist-info/entry_points.txt
pipenv-2025.0.0.dist-info/top_level.txt
pipenv-2025.0.0.dist-info/RECORD
