Metadata-Version: 2.4
Name: pipenv
Version: 2025.0.0
Summary: Python Development Workflow for Humans.
Author-email: Pipenv maintainer team <distutils-sig@python.org>
License: MIT License (MIT)
Project-URL: Documentation, https://pipenv.pypa.io/en/latest/
Project-URL: Homepage, https://github.com/pypa/pipenv
Project-URL: Source, https://github.com/pypa/pipenv.git
Classifier: License :: OSI Approved :: MIT License
Classifier: Programming Language :: Python
Classifier: Programming Language :: Python :: 3 :: Only
Classifier: Programming Language :: Python :: 3.9
Classifier: Programming Language :: Python :: 3.10
Classifier: Programming Language :: Python :: 3.11
Classifier: Programming Language :: Python :: 3.12
Classifier: Programming Language :: Python :: 3.13
Classifier: Programming Language :: Python :: Implementation :: CPython
Classifier: Programming Language :: Python :: Implementation :: PyPy
Requires-Python: >=3.9
License-File: LICENSE
License-File: NOTICES
Requires-Dist: certifi
Requires-Dist: packaging>=22
Requires-Dist: setuptools>=67
Requires-Dist: virtualenv>=20.24.2
Provides-Extra: dev
Requires-Dist: beautifulsoup4; extra == "dev"
Requires-Dist: black==24.3.0; extra == "dev"
Requires-Dist: flake8<4,>=3.3; extra == "dev"
Requires-Dist: invoke; extra == "dev"
Requires-Dist: parver; extra == "dev"
Requires-Dist: sphinx; extra == "dev"
Requires-Dist: towncrier; extra == "dev"
Provides-Extra: safety
Requires-Dist: safety>=3.0.0; extra == "safety"
Provides-Extra: tests
Requires-Dist: flaky; extra == "tests"
Requires-Dist: mock; extra == "tests"
Requires-Dist: pytest>=5; extra == "tests"
Requires-Dist: pytest-timeout; extra == "tests"
Requires-Dist: pytest-xdist; extra == "tests"
Dynamic: license-file
